{
  "format": "custom",
  "id": "sponsors",
  "label": "Sponsors",
  "repeatable": false,
  "status": true,
  "json": {
    "Main": {
      "sponsors": {
        "type": "Group",
        "config": {
          "label": "Sponsors",
          "repeat": true,
          "fields": {
            "name": {
              "type": "Text",
              "config": {
                "label": "Name",
                "placeholder": ""
              }
            },
            "highlight": {
              "type": "Boolean",
              "config": {
                "label": "Highlight",
                "default_value": false,
                "placeholder_true": "true",
                "placeholder_false": "false"
              }
            },
            "category": {
              "type": "Select",
              "config": {
                "label": "Category",
                "placeholder": "",
                "options": [
                  "TRACE Prime Sponsor",
                  "RAPID Prime Sponsor",
                  "Our Sponsors",
                  "Our Academic Partners"
                ]
              }
            },
            "logo": {
              "type": "Image",
              "config": {
                "label": "Logo",
                "constraint": {},
                "thumbnails": []
              }
            }
          }
        }
      }
    }
  }
}
